Workbook
Name Hourly_Wage__from_COL: 'Job Vacancies_Raw (2)'!$F$2
Name Job_Industry: 'Job Vacancies_Raw (2)'!$E$2
Name Job_Title: 'Job Vacancies_Raw (2)'!$B$2
Name Median_Wage: 'Job Vacancies_Raw (2)'!$D$2
Name Region: 'Job Vacancies_Raw (2)'!$2:$2
Name Slicer_Job_Industry: #N/A
Name Slicer_Region: #N/A
Name Slicer_Region1: #N/A
Name Slicer_Region2: #N/A
Name Vacancies: 'Job Vacancies_Raw (2)'!$C$2

Sheet SAP_Dashboard
A1: https://higher-education.us10.sapanalytics.cloud/sap/fpa/ui/tenants/81639/bo/story/DFB022842C6B3D75425368FEE0077FE2

Sheet Dashboard

Sheet Report
A6: Region | B6: Monthly Average Wage | C6: Monthly Cost of Living | D6: Wage Sufficiency Ratio
A7: Central MN | B7: 4000 | C7: 3850 | D7: 1.2270394
A8: Northeast MN | B8: 4200 | C8: 3950 | D8: 1.4663109
A9: Northwest MN | B9: 4150 | C9: 3850 | D9: 1.3815968
A10: Seven County Mpls-St Paul, MN | B10: 5200 | C10: 4600 | D10: 1.2995344
A11: Southeast MN | B11: 4500 | C11: 3900 | D11: 1.5319843
A12: Southwest MN | B12: 4300 | C12: 3800 | D12: 1.5038381

Sheet Pivot Tables
A1: Industry KPI Scorecard | F1: Statewide Seperations Distribution | J1: Statewide Labor Market Analysis
A2: Industry | B2: Vacancy Pressure Status | C2: Wage Sufficiency Status | F2: Row Labels | G2: Total | H2: % of Total Seperations | J2: Vacancy Rate | K2: Turn Over Rate | L2: Market Tightness
A3: Central Minnesota | B3: -1 | C3: 0 | F3: Layoffs and Discharges | G3: 308000 | H3: 0.31752577 | J3: 0.0096320298 | K3: 0.028962772 | L3: 0.3100624
A4: Northeast Minnesota | B4: -1 | C4: 0 | F4: Quits | G4: 662000 | H4: 0.68247423
A5: Northwest Minnesota | B5: -1 | C5: 0 | F5: Grand Total | G5: 970000 | H5: 1
A6: Seven County Mpls-St Paul, MN | B6: -1 | C6: 0
A7: Southeast Minnesota | B7: -1 | C7: 0
A8: Southwest Minnesota | B8: -1 | C8: 0
A10: Wage Sufficiency by Region
A11: Region | B11: Wage Sufficiency
A12: Central Minnesota | B12: 1.2270394
A13: Northeast Minnesota | B13: 1.4663109
A14: Northwest Minnesota | B14: 1.3815968
A15: Seven County Mpls-St Paul, MN | B15: 1.2995344
A16: Southeast Minnesota | B16: 1.5319843
A17: Southwest Minnesota | B17: 1.5038381
J18: Region | K18: All | R18: Region | S18: All
J19: Job Industry | K19: All | R19: Job Industry | S19: All
A20: Vacancy Pressure Heat Matrix (Region x Job Industry) | J20: Region Jobs KPI Scorecard | R20: Region Jobs KPI Scorecard
A21: Vacancy Pressure | B21: Region | J21: UI Claim Intensity | K21: Column Labels | R21: Region | S21: UI Claim Intensity
A22: Industry | B22: Central Minnesota | C22: Northeast Minnesota | D22: Northwest Minnesota | E22: Seven County Mpls-St Paul, MN | F22: Southeast Minnesota | G22: Southwest Minnesota | J22: Region | K22: Central Minnesota | L22: Northeast Minnesota | M22: Northwest Minnesota | N22: Seven County Mpls-St Paul, MN | O22: Southeast Minnesota | P22: Southwest Minnesota | R22: January | S22: 0.058874321
A23: Architecture and Engineering Occupations | B23: 0.0024915582 | C23: 0.0067842955 | D23: 0.0057325307 | E23: 0.0048324146 | F23: 0.0018683367 | G23: 0.0020535714 | J23: January | K23: 0.052370755 | L23: 0.080005068 | M23: 0.052384474 | N23: 0.052344474 | O23: 0.090227131 | P23: 0.077201999 | R23: February | S23: 0.034380233
A24: Arts, Design, Entertainment, Sports, and Media Occupations | B24: 0.0024970222 | C24: 0.0015563466 | D24: 0.0033088729 | E24: 0.0040422435 | F24: 0.0019771718 | G24: 0.0011415816 | J24: February | K24: 0.025495485 | L24: 0.049978061 | M24: 0.023081508 | N24: 0.035369217 | O24: 0.04395447 | P24: 0.034589778 | R24: March | S24: 0.034883956
A25: Building and Grounds Cleaning and Maintenance Occupations | B25: 0.0041252773 | C25: 0.0074033947 | D25: 0.011422327 | E25: 0.0033791239 | F25: 0.0013740437 | G25: 0.0074936224 | J25: March | K25: 0.026568253 | L25: 0.052450146 | M25: 0.02829484 | N25: 0.03464679 | O25: 0.044946094 | P25: 0.035442956 | R25: April | S25: 0.032757386
A26: Business and Financial Operations Occupations | B26: 0.0062671431 | C26: 0.0060534145 | D26: 0.0037606378 | E26: 0.011776782 | F26: 0.0033285416 | G26: 0.0033354592 | J26: April | K26: 0.02363584 | L26: 0.047910079 | M26: 0.021267925 | N26: 0.033919882 | O26: 0.043132348 | P26: 0.031652229 | R26: May | S26: 0.043047422
A27: Community and Social Service Occupations | B27: 0.0045460009 | C27: 0.0057868579 | D27: 0.006959622 | E27: 0.0089370694 | F27: 0.002489604 | G27: 0.0071109694 | J27: May | K27: 0.031297135 | L27: 0.055106019 | M27: 0.058580322 | N27: 0.035722683 | O27: 0.063874155 | P27: 0.067971678 | R27: June | S27: 0.077373701
A28: Computer and Mathematical Occupations | B28: 0.00056825012 | C28: 0.00069648661 | D28: 0.0010805729 | E28: 0.0082371717 | F28: 0.0017776407 | G28: 0.00070153061 | J28: June | K28: 0.062204826 | L28: 0.089171975 | M28: 0.060459151 | N28: 0.074779173 | O28: 0.10549313 | P28: 0.10527712 | R28: July | S28: 0.042901078
A29: Construction and Extraction Occupations | B29: 0.0092340644 | C29: 0.0013585788 | D29: 0.0079547258 | E29: 0.0023225904 | F29: 0.00091602915 | G29: 0.0019834184 | J29: July | K29: 0.027466772 | L29: 0.042301595 | M29: 0.041547027 | N29: 0.043084078 | O29: 0.058207368 | P29: 0.052794602 | R29: August | S29: 0.031874384
A30: Educational Instruction and Library Occupations | B30: 0.011911397 | C30: 0.0070594507 | D30: 0.011074346 | E30: 0.010354697 | F30: 0.0052376914 | G30: 0.010070153 | J30: August | K30: 0.020608545 | L30: 0.029586319 | M30: 0.021085805 | N30: 0.034529212 | O30: 0.045872586 | P30: 0.030072419 | R30: September | S30: 0.030379804 | BS30: Region Jobs KPI Scorecard
A31: Farming, Fishing, and Forestry Occupations | B31: 0.0011091805 | D31: 0.00178264 | E31: 2.7862169e-05 | F31: 9.9765551e-05 | G31: 0.0010841837 | J31: September | K31: 0.021283177 | L31: 0.03786891 | M31: 0.0252621 | N31: 0.030700169 | O31: 0.036048163 | P31: 0.038968042 | R31: October | S31: 0.034291692 | BS31: UI Claimants | BT31: Column Labels
A32: Food Preparation and Serving Related Occupations | B32: 0.02919385 | C32: 0.035469226 | D32: 0.042160657 | E32: 0.034882321 | F32: 0.021150297 | G32: 0.022251276 | J32: October | K32: 0.026455468 | L32: 0.046952271 | M32: 0.035473562 | N32: 0.033618029 | O32: 0.041735804 | P32: 0.033879256 | R32: November | S32: 0.05860609 | BS32: Region | BT32: January | BU32: February | BV32: March | BW32: April | BX32: May | BY32: June | BZ32: July | CA32: August | CB32: September | CC32: October | CD32: November | CE32: December
A33: Healthcare Practitioners and Technical Occupations | B33: 0.023440317 | C33: 0.027429534 | D33: 0.017515049 | E33: 0.025697836 | F33: 0.022846311 | G33: 0.012589286 | J33: November | K33: 0.056392429 | L33: 0.093981728 | M33: 0.084031511 | N33: 0.044156075 | O33: 0.08741727 | P33: 0.081137668 | R33: December | S33: 0.075806211 | BS33: Construction and Extraction Occupations | BT33: 64943 | BU33: 29009 | BV33: 27551 | BW33: 23598 | BX33: 19926 | BY33: 18038 | BZ33: 18540 | CA33: 15291 | CB33: 19724 | CC33: 24327 | CD33: 71129 | CE33: 94730
A34: Healthcare Support Occupations | B34: 0.022118043 | C34: 0.025047722 | D34: 0.019181695 | E34: 0.016353979 | F34: 0.0085571634 | G34: 0.017825255 | J34: December | K34: 0.075760442 | L34: 0.10514746 | M34: 0.092772214 | N34: 0.056055646 | O34: 0.11837604 | P34: 0.13611094 | BS34: Unknown | BT34: 19778 | BU34: 12563 | BV34: 12366 | BW34: 11539 | BX34: 13431 | BY34: 18736 | BZ34: 15258 | CA34: 11578 | CB34: 12619 | CC34: 13533 | CD34: 22100 | CE34: 26734
A35: Installation, Maintenance, and Repair Occupations | B35: 0.010829536 | C35: 0.0079279093 | D35: 0.01251511 | E35: 0.0075495334 | F35: 0.0055551273 | G35: 0.011332908 | BS35: Transportation and Material Moving Occupations | BT35: 11879 | BU35: 6085 | BV35: 7736 | BW35: 6616 | BX35: 8932 | BY35: 27416 | BZ35: 10224 | CA35: 7037 | CB35: 3998 | CC35: 5629 | CD35: 15033 | CE35: 21501
A36: Legal Occupations | B36: 0.00011474281 | D36: 0.00029303672 | E36: 0.00096626003 | F36: 0.00017232232 | BS36: Production Occupations | BT36: 12766 | BU36: 7710 | BV36: 8737 | BW36: 7548 | BX36: 8992 | BY36: 10779 | BZ36: 14696 | CA36: 9120 | CB36: 10702 | CC36: 9510 | CD36: 11076 | CE36: 17796
A37: Life, Physical, and Social Science Occupations | B37: 0.0015189763 | C37: 0.0013069872 | D37: 0.00073259179 | E37: 0.0019013144 | F37: 0.0022492597 | G37: 0.0010012755 | BS37: Food Preparation and Serving Related Occupations | BT37: 10156 | BU37: 6780 | BV37: 8393 | BW37: 6269 | BX37: 12991 | BY37: 27154 | BZ37: 10259 | CA37: 7591 | CB37: 5825 | CC37: 6928 | CD37: 7511 | CE37: 12648
A38: Management Occupations | B38: 0.0025461976 | C38: 0.0044196805 | D38: 0.0027899537 | E38: 0.014887314 | F38: 0.0050971127 | G38: 0.0030867347 | BS38: Building & Grounds Cleaning & Maintenance Occup. | BT38: 5280 | BU38: 2757 | BV38: 2175 | BW38: 2093 | BX38: 1692 | BY38: 1728 | BZ38: 1684 | CA38: 1710 | CB38: 1629 | CC38: 3546 | CD38: 8994 | CE38: 8936
A39: Office and Administrative Support Occupations | B39: 0.014353779 | C39: 0.0073690003 | D39: 0.0090597184 | E39: 0.0098554065 | F39: 0.0074098596 | G39: 0.0066390306 | BS39: Office and Administrative Support Occupations | BT39: 9119 | BU39: 6803 | BV39: 6589 | BW39: 6623 | BX39: 7710 | BY39: 14255 | BZ39: 8700 | CA39: 7447 | CB39: 6327 | CC39: 7417 | CD39: 7693 | CE39: 8168
A40: Personal Care and Service Occupations | B40: 0.0063381744 | C40: 0.010645067 | D40: 0.0056409568 | E40: 0.007239706 | F40: 0.0038908565 | G40: 0.0016645408 | BS40: Sales and Related Occupations | BT40: 9491 | BU40: 6951 | BV40: 6429 | BW40: 7075 | BX40: 6793 | BY40: 7204 | BZ40: 7218 | CA40: 6693 | CB40: 6523 | CC40: 6833 | CD40: 7039 | CE40: 7399
A41: Production Occupations | B41: 0.0081959152 | C41: 0.001633734 | D41: 0.0094870637 | E41: 0.0062556142 | F41: 0.0077545042 | G41: 0.0079655612 | BS41: Management Occupations | BT41: 8181 | BU41: 6362 | BV41: 6106 | BW41: 6649 | BX41: 6563 | BY41: 6461 | BZ41: 6750 | CA41: 6212 | CB41: 6469 | CC41: 6680 | CD41: 7384 | CE41: 6947
A42: Protective Service Occupations | B42: 0.0028357866 | C42: 0.0020120724 | D42: 0.0032722433 | E42: 0.0025354574 | F42: 0.0014148569 | G42: 0.0038329082 | BS42: Education, Training, and Library Occupations | BT42: 3455 | BU42: 1426 | BV42: 2168 | BW42: 2337 | BX42: 26173 | BY42: 88619 | BZ42: 19226 | CA42: 8212 | CB42: 2624 | CC42: 2534 | CD42: 1731 | CE42: 5706
A43: Sales and Related Occupations | B43: 0.030341278 | C43: 0.034514781 | D43: 0.033790796 | E43: 0.024479702 | F43: 0.013477419 | G43: 0.018418367 | L43: Sum of Claimants | M43: Column Labels | BS43: Installation, Maintenance, and Repair Occupations | BT43: 4514 | BU43: 3581 | BV43: 3693 | BW43: 2943 | BX43: 2595 | BY43: 2582 | BZ43: 2931 | CA43: 2528 | CB43: 2901 | CC43: 2673 | CD43: 4122 | CE43: 5659
A44: Transportation and Material Moving Occupations | B44: 0.018451737 | C44: 0.0093466784 | D44: 0.011794728 | E44: 0.010566449 | F44: 0.0082624015 | G44: 0.01966199 | M44: Jan | N44: Feb | O44: Mar | P44: Apr | Q44: May | R44: Jun | S44: Jul | T44: Aug | U44: Sep | V44: Oct | W44: Nov | X44: Dec | Y44: Grand Total | BS44: Farming, Fishing, and Forestry Occupations | BT44: 2766 | BU44: 893 | BV44: 1052 | BW44: 969 | BX44: 332 | BY44: 251 | BZ44: 375 | CA44: 280 | CB44: 163 | CC44: 1028 | CD44: 3735 | CE44: 4630
A45: Unknown | B45: 0.0018085653 | C45: 0.0013929732 | D45: 0.0023442937 | E45: 0.0028452847 | F45: 0.00075731123 | G45: 0.0017091837 | BS45: Healthcare Support Occupations | BT45: 4338 | BU45: 3611 | BV45: 3621 | BW45: 4300 | BX45: 4599 | BY45: 5302 | BZ45: 4532 | CA45: 4125 | CB45: 3778 | CC45: 4275 | CD45: 3602 | CE45: 4209
A46: Region | B46: All | L46: Row Labels | BS46: Business and Financial Operations Occupations | BT46: 3441 | BU46: 2945 | BV46: 2762 | BW46: 3949 | BX46: 3850 | BY46: 2950 | BZ46: 3391 | CA46: 2750 | CB46: 3068 | CC46: 3067 | CD46: 2889 | CE46: 2683
L47: Architecture and Engineering Occupations | M47: 1418 | N47: 1204 | O47: 797 | P47: 1033 | Q47: 899 | R47: 1100 | S47: 1784 | T47: 861 | U47: 874 | V47: 1132 | W47: 1141 | X47: 1130 | Y47: 13373 | BS47: Computer and Mathematical Occupations | BT47: 2851 | BU47: 2030 | BV47: 2207 | BW47: 2440 | BX47: 2550 | BY47: 2404 | BZ47: 2584 | CA47: 2637 | CB47: 2302 | CC47: 2382 | CD47: 1958 | CE47: 2041
A48: Industry | B48: Vacancies | L48: Arts, Design, Entertainment, Sports, and Media Occ | M48: 2629 | N48: 1972 | O48: 1556 | P48: 1665 | Q48: 1777 | R48: 2057 | S48: 1864 | T48: 1652 | U48: 1463 | V48: 1445 | W48: 1577 | X48: 1883 | Y48: 21540 | BS48: Arts, Design, Entertainment, Sports, and Media Occ | BT48: 2629 | BU48: 1972 | BV48: 1556 | BW48: 1665 | BX48: 1777 | BY48: 2057 | BZ48: 1864 | CA48: 1652 | CB48: 1463 | CC48: 1445 | CD48: 1577 | CE48: 1883
A49: Food Preparation and Serving Related Occupations | B49: 55826 | L49: Building & Grounds Cleaning & Maintenance Occup. | M49: 5280 | N49: 2757 | O49: 2175 | P49: 2093 | Q49: 1692 | R49: 1728 | S49: 1684 | T49: 1710 | U49: 1629 | V49: 3546 | W49: 8994 | X49: 8936 | Y49: 42224 | BS49: Healthcare Practitioners and Technical Occupations | BT49: 1899 | BU49: 1554 | BV49: 1797 | BW49: 1583 | BX49: 1717 | BY49: 3419 | BZ49: 1852 | CA49: 1617 | CB49: 1559 | CC49: 1616 | CD49: 1326 | CE49: 1262
A50: Sales and Related Occupations | B50: 42927 | L50: Business and Financial Operations Occupations | M50: 3441 | N50: 2945 | O50: 2762 | P50: 3949 | Q50: 3850 | R50: 2950 | S50: 3391 | T50: 2750 | U50: 3068 | V50: 3067 | W50: 2889 | X50: 2683 | Y50: 37745 | BS50: Architecture and Engineering Occupations | BT50: 1418 | BU50: 1204 | BV50: 797 | BW50: 1033 | BX50: 899 | BY50: 1100 | BZ50: 1784 | CA50: 861 | CB50: 874 | CC50: 1132 | CD50: 1141 | CE50: 1130
A51: Healthcare Practitioners and Technical Occupations | B51: 40419 | L51: Community and Social Services Occupations | M51: 969 | N51: 630 | O51: 763 | P51: 867 | Q51: 943 | R51: 1470 | S51: 1590 | T51: 1138 | U51: 721 | V51: 1004 | W51: 930 | X51: 644 | Y51: 11669 | BS51: Personal Care and Service Occupations | BT51: 989 | BU51: 777 | BV51: 922 | BW51: 892 | BX51: 986 | BY51: 1136 | BZ51: 1074 | CA51: 707 | CB51: 767 | CC51: 747 | CD51: 895 | CE51: 824
A52: Healthcare Support Occupations | B52: 29459 | L52: Computer and Mathematical Occupations | M52: 2851 | N52: 2030 | O52: 2207 | P52: 2440 | Q52: 2550 | R52: 2404 | S52: 2584 | T52: 2637 | U52: 2302 | V52: 2382 | W52: 1958 | X52: 2041 | Y52: 28386 | BS52: Protective Service Occupations | BT52: 644 | BU52: 525 | BV52: 581 | BW52: 595 | BX52: 525 | BY52: 644 | BZ52: 560 | CA52: 511 | CB52: 518 | CC52: 532 | CD52: 766 | CE52: 735
A53: Transportation and Material Moving Occupations | B53: 20782 | L53: Construction and Extraction Occupations | M53: 64943 | N53: 29009 | O53: 27551 | P53: 23598 | Q53: 19926 | R53: 18038 | S53: 18540 | T53: 15291 | U53: 19724 | V53: 24327 | W53: 71129 | X53: 94730 | Y53: 426806 | BS53: Community and Social Services Occupations | BT53: 969 | BU53: 630 | BV53: 763 | BW53: 867 | BX53: 943 | BY53: 1470 | BZ53: 1590 | CA53: 1138 | CB53: 721 | CC53: 1004 | CD53: 930 | CE53: 644
A54: Grand Total | B54: 189413 | L54: Education, Training, and Library Occupations | M54: 3455 | N54: 1426 | O54: 2168 | P54: 2337 | Q54: 26173 | R54: 88619 | S54: 19226 | T54: 8212 | U54: 2624 | V54: 2534 | W54: 1731 | X54: 5706 | Y54: 164211 | BS54: Legal Occupations | BT54: 385 | BU54: 378 | BV54: 448 | BW54: 476 | BX54: 336 | BY54: 378 | BZ54: 329 | CA54: 329 | CB54: 413 | CC54: 329 | CD54: 245 | CE54: 273
L55: Farming, Fishing, and Forestry Occupations | M55: 2766 | N55: 893 | O55: 1052 | P55: 969 | Q55: 332 | R55: 251 | S55: 375 | T55: 280 | U55: 163 | V55: 1028 | W55: 3735 | X55: 4630 | Y55: 16474 | BS55: Life, Physical, and Social Science Occupations | BT55: 231 | BU55: 182 | BV55: 364 | BW55: 266 | BX55: 287 | BY55: 238 | BZ55: 322 | CA55: 238 | CB55: 350 | CC55: 336 | CD55: 245 | CE55: 238
L56: Food Preparation and Serving Related Occupations | M56: 10156 | N56: 6780 | O56: 8393 | P56: 6269 | Q56: 12991 | R56: 27154 | S56: 10259 | T56: 7591 | U56: 5825 | V56: 6928 | W56: 7511 | X56: 12648 | Y56: 122505 | BS56: Military Specific Occupations | CC56: 77
L57: Healthcare Practitioners and Technical Occupations | M57: 1899 | N57: 1554 | O57: 1797 | P57: 1583 | Q57: 1717 | R57: 3419 | S57: 1852 | T57: 1617 | U57: 1559 | V57: 1616 | W57: 1326 | X57: 1262 | Y57: 21201
L58: Healthcare Support Occupations | M58: 4338 | N58: 3611 | O58: 3621 | P58: 4300 | Q58: 4599 | R58: 5302 | S58: 4532 | T58: 4125 | U58: 3778 | V58: 4275 | W58: 3602 | X58: 4209 | Y58: 50292
L59: Installation, Maintenance, and Repair Occupations | M59: 4514 | N59: 3581 | O59: 3693 | P59: 2943 | Q59: 2595 | R59: 2582 | S59: 2931 | T59: 2528 | U59: 2901 | V59: 2673 | W59: 4122 | X59: 5659 | Y59: 40722
L60: Legal Occupations | M60: 385 | N60: 378 | O60: 448 | P60: 476 | Q60: 336 | R60: 378 | S60: 329 | T60: 329 | U60: 413 | V60: 329 | W60: 245 | X60: 273 | Y60: 4319
L61: Life, Physical, and Social Science Occupations | M61: 231 | N61: 182 | O61: 364 | P61: 266 | Q61: 287 | R61: 238 | S61: 322 | T61: 238 | U61: 350 | V61: 336 | W61: 245 | X61: 238 | Y61: 3297
L62: Management Occupations | M62: 8181 | N62: 6362 | O62: 6106 | P62: 6649 | Q62: 6563 | R62: 6461 | S62: 6750 | T62: 6212 | U62: 6469 | V62: 6680 | W62: 7384 | X62: 6947 | Y62: 80764
L63: Military Specific Occupations | V63: 77 | Y63: 77
L64: Office and Administrative Support Occupations | M64: 9119 | N64: 6803 | O64: 6589 | P64: 6623 | Q64: 7710 | R64: 14255 | S64: 8700 | T64: 7447 | U64: 6327 | V64: 7417 | W64: 7693 | X64: 8168 | Y64: 96851
L65: Personal Care and Service Occupations | M65: 989 | N65: 777 | O65: 922 | P65: 892 | Q65: 986 | R65: 1136 | S65: 1074 | T65: 707 | U65: 767 | V65: 747 | W65: 895 | X65: 824 | Y65: 10716
L66: Production Occupations | M66: 12766 | N66: 7710 | O66: 8737 | P66: 7548 | Q66: 8992 | R66: 10779 | S66: 14696 | T66: 9120 | U66: 10702 | V66: 9510 | W66: 11076 | X66: 17796 | Y66: 129432
L67: Protective Service Occupations | M67: 644 | N67: 525 | O67: 581 | P67: 595 | Q67: 525 | R67: 644 | S67: 560 | T67: 511 | U67: 518 | V67: 532 | W67: 766 | X67: 735 | Y67: 7136
L68: Sales and Related Occupations | M68: 9491 | N68: 6951 | O68: 6429 | P68: 7075 | Q68: 6793 | R68: 7204 | S68: 7218 | T68: 6693 | U68: 6523 | V68: 6833 | W68: 7039 | X68: 7399 | Y68: 85648
L69: Transportation and Material Moving Occupations | M69: 11879 | N69: 6085 | O69: 7736 | P69: 6616 | Q69: 8932 | R69: 27416 | S69: 10224 | T69: 7037 | U69: 3998 | V69: 5629 | W69: 15033 | X69: 21501 | Y69: 132086
L70: Unknown | M70: 19778 | N70: 12563 | O70: 12366 | P70: 11539 | Q70: 13431 | R70: 18736 | S70: 15258 | T70: 11578 | U70: 12619 | V70: 13533 | W70: 22100 | X70: 26734 | Y70: 190235
L71: Grand Total | M71: 182122 | N71: 106728 | O71: 108813 | P71: 102325 | Q71: 134599 | R71: 244321 | S71: 135743 | T71: 100264 | U71: 95317 | V71: 107580 | W71: 183121 | X71: 236776 | Y71: 1737709

Sheet Data Dictionary
A1: Raw Data Tables Data Dictionary
A2: Table | B2: Field | C2: Type | D2: Description | E2: Sample Values | F2: Transformations/Notes
A3: Job Turnover_Raw | B3: Activity | C3: Text | D3: Turnover metric for the row | E3: Hires; Job Openings; Quits; Total Separations | F3: Used to filter measures (e.g., Total Hires, Total Quits)
A4: Job Turnover_Raw | B4: Month Year | C4: Date | D4: Reference month for the activity | E4: 1/1/2024; 2/1/2024 | F4: Related to Calendar[Date]
A5: Job Turnover_Raw | B5: Total | C5: Whole Number | D5: Count for the activity in that period | E5: 111; 145; 77 | F5: Summed in measures; format as Whole Number
A6: Job Vacancies_Raw | B6: Region | C6: Text | D6: Planning Region name | E6: Central Minnesota; Northwest Minnesota | F6: Join key to DimPlanningRegion[Planning Region]
A7: Job Vacancies_Raw | B7: Year | C7: Whole Number | D7: Survey/reference year | E7: 2023; 2024 | F7: Relate to Calendar[Year] if needed (annual grain)
A8: Job Vacancies_Raw | B8: occcode | C8: Text | D8: SOC occupation code (2018 SOC) | E8: 15-1252; 11-2033 | F8: Used to derive Job Industry via two-digit mapping
A9: Job Vacancies_Raw | B9: Job Title | C9: Text | D9: SOC occupation title | E9: Software Developers; Office & Admin Support | F9: —
A10: Job Vacancies_Raw | B10: Vacancies | C10: Whole Number | D10: Number of openings in region & occupation | E10: 175; 182 | F10: Measure [Vacancies] = SUM(...)
A11: Job Vacancies_Raw | B11: medianwage | C11: Decimal | D11: Median advertised wage for the occupation | E11: 28.50; 31.75 | F11: Used in Wage Sufficiency numerator
A12: Job Vacancies_Raw | B12: meanwage | C12: Decimal | D12: Mean advertised wage for the occupation | E12: 30.1 | F12: Informational
A13: Job Vacancies_Raw | B13: Job Industry | C13: Text | D13: SOC major group label derived from occcode | E13: Computer and Mathematical Occupations | F13: Custom column based on first two digits of occcode
A14: UI Claim_Raw | B14: Region | C14: Text | D14: EDR short name | E14: Central; Northwest; Arrowhead | F14: Trimmed; mapped to Planning Region via DimMap_Region
A15: UI Claim_Raw | B15: Date | C15: Date | D15: Claim snapshot month | E15: 45444 | F15: Related to Calendar[Date]
A16: UI Claim_Raw | B16: Job Title | C16: Text | D16: Occupation grouping for claims (if present) | E16: Office/Admin Support | F16: Optional
A17: UI Claim_Raw | B17: Current | C17: Whole Number | D17: Active UI claimants count | E17: 1234 | F17: Converted from text → number; measure [UI Claimants] sums this
A18: UI Claim_Raw | B18: Planning Region | C18: Calculated Text | D18: Normalized planning region label | E18: Central Minnesota | F18: LOOKUPVALUE from DimMap_Region (added calc column)
A19: Employment_Raw | B19: Region | C19: Text | D19: EDR short name | E19: Central | F19: Trim + map to Planning Region
A20: Employment_Raw | B20: Year | C20: Whole Number | D20: Reference year | E20: 2024 | F20: Relate to Calendar[Year] if annual
A21: Employment_Raw | B21: Month | C21: Whole Number | D21: Month number 1–12 (if present) | E21: 6 | F21: If Month exists, create [Date]=DATE(Year,Month,1)
A22: Employment_Raw | B22: Employment Total | C22: Whole Number | D22: Employed persons | E22: 250000 | F22: Measure [Employment] = SUM(...); part of Labor Force
A23: Unemployment_Raw | B23: Region | C23: Text | D23: EDR short name | E23: Central | F23: Trim + map to Planning Region
A24: Unemployment_Raw | B24: Year | C24: Whole Number | D24: Reference year | E24: 2024 | F24: Relate to Calendar[Year] if annual
A25: Unemployment_Raw | B25: Month | C25: Whole Number | D25: Month number 1–12 (if present) | E25: 6 | F25: If Month exists, create [Date]=DATE(Year,Month,1)
A26: Unemployment_Raw | B26: Unemployment Total | C26: Whole Number | D26: Unemployed persons | E26: 9800 | F26: Measure [Unemployment] = SUM(...); part of Labor Force
A27: Cost of Living_Raw | B27: Area | C27: Text | D27: Planning Region label | E27: Central Minnesota | F27: Join to DimPlanningRegion[Planning Region]
A28: Cost of Living_Raw | B28: Year | C28: Whole Number | D28: Reference year for COL | E28: 2024 | F28: Annual grain
A29: Cost of Living_Raw | B29: Hourly Wage | C29: Decimal | D29: Living-wage estimate (hourly) | E29: 21.75 | F29: Used in Wage Sufficiency denominator
A30: Dim_Region | B30: Planning Region | C30: Text | D30: Unique list of planning regions | E30: Central Minnesota; Northwest Minnesota | F30: True dimension (one row per region)
A31: Calendar | B31: Date | C31: Date | D31: Calendar date (continuous) | E31: 45352 | F31: Marked as Date Table; primary relationship key. Only exists in Power Pivot data model
A32: Calendar | B32: Year | C32: Whole Number | D32: Calendar year | E32: 2024 | F32: Helper for annual-grain facts
A33: Calendar | B33: Quarter | C33: Text | D33: Quarter label | E33: Q1; Q2; Q3; Q4 | F33: ="Q"&FORMAT([Date],"Q")
A34: Calendar | B34: Quarter Number | C34: Whole Number | D34: Quarter number | E34: 1; 2; 3; 4 | F34: =QUARTER([Date])
A35: Calendar | B35: Month Number | C35: Whole Number | D35: Month number | E35: 1..12 | F35: =MONTH([Date])
A36: Calendar | B36: Month | C36: Text | D36: Abbreviated month | E36: Mar; Jun | F36: =FORMAT([Date],"MMM")
A37: Calendar | B37: Year-Quarter | C37: Text | D37: Year & quarter label | E37: 2024 Q3 | F37: =FORMAT([Date],"YYYY")&" Q"&FORMAT([Date],"Q")
A38: Calendar | B38: YearMonth | C38: Text | D38: Year-month label | E38: 2024-03 | F38: =FORMAT([Date],"YYYY-MM")
A39: Calendar | B39: YearQuarter Key | C39: Whole Number | D39: Sort key for Year-Quarter | E39: 20241; 20242 | F39: =YEAR([Date])*10+QUARTER([Date])
A41: Measures Data Dictionary
A42: Measure Name | B42: Definition (Plain-English) | C42: DAX Formula (Power Pivot) | D42: Inputs / Notes | E42: Inputs / Notes2 | F42: Format
A43: COL Hourly | B43: Living-wage estimate (hourly) for the selected region(s) | C43: MEDIAN of Cost of Living hourly wage | D43: =MEDIAN('Cost of Living_Raw'[Hourly Wage]) | E43: Used as denominator in Wage Sufficiency | F43: Currency (no decimals)
A44: Employment | B44: Employed persons (headcount) | C44: SUM of Employment total | D44: =SUM('Employment_Raw'[Employment Total]) | E44: Part of Labor Force | F44: Number (comma)
A45: Unemployment | B45: Unemployed persons (headcount) | C45: SUM of Unemployment total | D45: =SUM('Unemployment_Raw'[Unemployment Total]) | E45: Part of Labor Force | F45: Number (comma)
A46: Labor Force | B46: Size of labor force | C46: Employment + Unemployment | D46: =[Employment]+[Unemployment] | E46: Derived total | F46: Number (comma)
A47: Vacancies_measure | B47: Total job openings | C47: SUM of vacancies | D47: =SUM('Job Vacancies_Raw'[Vacancies]) | E47: Core input to Vacancy Pressure | F47: Number (comma)
A48: Median Wage | B48: Median posted wage for current filter | C48: MEDIAN of medianwage by Job Title | D48: =MEDIANX(VALUES('Job Vacancies_Raw'[Job Title]), CALCULATE(MEDIAN('Job Vacancies_Raw'[medianwage]))) | E48: Use when multiple occupations/regions are filtered | F48: Currency (2 decimals)
A49: Wage Sufficiency | B49: Wage relative to living wage | C49: Median Wage ÷ COL Hourly | D49: =[Median Wage]/[COL Hourly] | E49: Key KPI; target ≈ 1.70 | F49: Decimal (2) or % (custom)
A50: UI Claimants | B50: Active UI claimants | C50: SUM of current claimants | D50: =SUM('UI Claim_Raw'[Current]) | E50: Column name may be [Current] or [Claimants] | F50: Number (comma)
A51: UI Claim Intensity | B51: Share of labor force drawing UI | C51: UI Claimants ÷ Labor Force | D51: =DIVIDE([UI Claimants],[Labor Force]) | E51: Rate of benefit use | F51: Percent (1)
A52: Vacancy Pressure | B52: Openings per claimant | C52: Vacancies ÷ UI Claimants | D52: =DIVIDE([Vacancies_measure],[UI Claimants]) | E52: Higher = harder to hire | F52: Decimal (3)
A53: Vacancy Rate | B53: Openings relative to employment | C53: Vacancies ÷ Employment | D53: =DIVIDE([Vacancies_measure],[Employment]) | E53: Alternative tightness metric | F53: Percent (1)
... A62: Market Tightness | B62: Openings per unemployed | C62: Vacancies ÷ Unemployment | D62: =DIVIDE([Vacancies_measure],[Unemployment]) | E62: Classic tightness metric | F62: Decimal (2)

Sheet DIM_Region_Raw
A1: Planning Region
A2: Northwest Minnesota
A3: Northeast Minnesota
A4: Central Minnesota
A5: Southwest Minnesota
A6: Southeast Minnesota
A7: Seven County Mpls-St Paul, MN

Sheet Region_Raw
A1: Region Name | B1: County | C1: Planning Region
A2: EDR 01 Northwest | B2: Kittson County | C2: Northwest Minnesota
A3: EDR 01 Northwest | B3: Marshall County | C3: Northwest Minnesota
A4: EDR 01 Northwest | B4: Norman County | C4: Northwest Minnesota
A5: EDR 01 Northwest | B5: Pennington County | C5: Northwest Minnesota
A6: EDR 01 Northwest | B6: Polk County | C6: Northwest Minnesota
A7: EDR 01 Northwest | B7: Red Lake County | C7: Northwest Minnesota
A8: EDR 01 Northwest | B8: Roseau County | C8: Northwest Minnesota
A9: EDR 02 Headwaters | B9: Beltrami County | C9: Northwest Minnesota
A10: EDR 02 Headwaters | B10: Clearwater County | C10: Northwest Minnesota
A11: EDR 02 Headwaters | B11: Hubbard County | C11: Northwest Minnesota
A12: EDR 02 Headwaters | B12: Lake of the Woods County | C12: Northwest Minnesota
... A88: EDR 11 7 County Twin Cities | B88: Washington County | C88: Seven County Mpls-St Paul, MN

Sheet Job Vacancies_Raw (2)
A1: Region | B1: Job Title | C1: Vacancies | D1: medianwage | E1: Job Industry | F1: Column1 | G1: Column2
A2: Region | B2: Job Title | C2: Vacancies | D2: Median Wage | E2: Job Industry | F2: Hourly Wage (from COL) | G2: Wage Suffficeny Ratio
A3: Seven County Mpls-St Paul, MN | B3: Management Occupations | C3: 4460 | D3: 42.5 | E3: Management Occupations | F3: =_xlfn.XLOOKUP(Job_Vacancies6[[#This Row],[Region]], 'Cost of Living_Raw'!A:A, 'Cost of Living_Raw'!C:C, "") -> 19.33 | G3: =(D3 / F3) -> 2.1986549
A4: Seven County Mpls-St Paul, MN | B4: Top Executives | C4: 144 | D4: 39.41 | E4: Management Occupations | F4: =_xlfn.XLOOKUP(Job_Vacancies6[[#This Row],[Region]], 'Cost of Living_Raw'!A:A, 'Cost of Living_Raw'!C:C, "") -> 19.33 | G4: =(D4 / F4) -> 2.0387998
A5: Seven County Mpls-St Paul, MN | B5: Chief Executives | C5: 5 | D5: 44.59 | E5: Management Occupations | F5: =_xlfn.XLOOKUP(Job_Vacancies6[[#This Row],[Region]], 'Cost of Living_Raw'!A:A, 'Cost of Living_Raw'!C:C, "") -> 19.33 | G5: =(D5 / F5) -> 2.306777
A6: Seven County Mpls-St Paul, MN | B6: General and Operations Managers | C6: 139 | D6: 38.7 | E6: Management Occupations | F6: =_xlfn.XLOOKUP(Job_Vacancies6[[#This Row],[Region]], 'Cost of Living_Raw'!A:A, 'Cost of Living_Raw'!C:C, "") -> 19.33 | G6: =(D6 / F6) -> 2.0020693
A7: Seven County Mpls-St Paul, MN | B7: Advertising, Marketing, Promotions, Public Relatio | C7: 991 | D7: 47.63 | E7: Management Occupations | F7: =_xlfn.XLOOKUP(Job_Vacancies6[[#This Row],[Region]], 'Cost of Living_Raw'!A:A, 'Cost of Living_Raw'!C:C, "") -> 19.33 | G7: =(D7 / F7) -> 2.4640455
A8: Seven County Mpls-St Paul, MN | B8: Advertising and Promotions Managers | C8: 9 | D8: 41.88 | E8: Management Occupations | F8: =_xlfn.XLOOKUP(Job_Vacancies6[[#This Row],[Region]], 'Cost of Living_Raw'!A:A, 'Cost of Living_Raw'!C:C, "") -> 19.33 | G8: =(D8 / F8) -> 2.1665804
A9: Seven County Mpls-St Paul, MN | B9: Marketing Managers | C9: 597 | D9: 48.59 | E9: Management Occupations | F9: =_xlfn.XLOOKUP(Job_Vacancies6[[#This Row],[Region]], 'Cost of Living_Raw'!A:A, 'Cost of Living_Raw'!C:C, "") -> 19.33 | G9: =(D9 / F9) -> 2.5137093
A10: Seven County Mpls-St Paul, MN | B10: Sales Managers | C10: 217 | D10: 53.79 | E10: Management Occupations | F10: =_xlfn.XLOOKUP(Job_Vacancies6[[#This Row],[Region]], 'Cost of Living_Raw'!A:A, 'Cost of Living_Raw'!C:C, "") -> 19.33 | G10: =(D10 / F10) -> 2.7827212
A11: Seven County Mpls-St Paul, MN | B11: Public Relations Managers | C11: 25 | D11: 44.54 | E11: Management Occupations | F11: =_xlfn.XLOOKUP(Job_Vacancies6[[#This Row],[Region]], 'Cost of Living_Raw'!A:A, 'Cost of Living_Raw'!C:C, "") -> 19.33 | G11: =(D11 / F11) -> 2.3041904
A12: Seven County Mpls-St Paul, MN | B12: Fundraising Managers | C12: 144 | D12: 39.1 | E12: Management Occupations | F12: =_xlfn.XLOOKUP(Job_Vacancies6[[#This Row],[Region]], 'Cost of Living_Raw'!A:A, 'Cost of Living_Raw'!C:C, "") -> 19.33 | G12: =(D12 / F12) -> 2.0227625
A13: Seven County Mpls-St Paul, MN | B13: Operations Specialties Managers | C13: 1605 | D13: 55.3 | E13: Management Occupations | F13: =_xlfn.XLOOKUP(Job_Vacancies6[[#This Row],[Region]], 'Cost of Living_Raw'!A:A, 'Cost of Living_Raw'!C:C, "") -> 19.33 | G13: =(D13 / F13) -> 2.8608381
A14: Seven County Mpls-St Paul, MN | B14: Administrative Services Managers | C14: 151 | D14: 46.96 | E14: Management Occupations | F14: =_xlfn.XLOOKUP(Job_Vacancies6[[#This Row],[Region]], 'Cost of Living_Raw'!A:A, 'Cost of Living_Raw'!C:C, "") -> 19.33 | G14: =(D14 / F14) -> 2.4293844
... A1812: Southwest Minnesota | B1812: Welders, Cutters, Solderers, and Brazers | C1812: 32 | D1812: 25.36 | E1812: Production Occupations | F1812: =_xlfn.XLOOKUP(Job_Vacancies6[[#This Row],[Region]], 'Cost of Living_Raw'!A:A, 'Cost of Living_Raw'!C:C, "") -> 14.33 | G1812: =(D1812 / F1812) -> 1.7697139
A1813: Southwest Minnesota | B1813: Printing Workers | C1813: 4 | E1813: Production Occupations | F1813: =_xlfn.XLOOKUP(Job_Vacancies6[[#This Row],[Region]], 'Cost of Living_Raw'!A:A, 'Cost of Living_Raw'!C:C, "") -> 14.33 | G1813: =(D1813 / F1813) -> 0
A1814: Southwest Minnesota | B1814: Textile, Apparel, and Furnishings Workers | C1814: 85 | D1814: 10 | E1814: Production Occupations | F1814: =_xlfn.XLOOKUP(Job_Vacancies6[[#This Row],[Region]], 'Cost of Living_Raw'!A:A, 'Cost of Living_Raw'!C:C, "") -> 14.33 | G1814: =(D1814 / F1814) -> 0.69783671
A1815: Southwest Minnesota | B1815: Laundry and Dry-Cleaning Workers | C1815: 85 | D1815: 10 | E1815: Production Occupations | F1815: =_xlfn.XLOOKUP(Job_Vacancies6[[#This Row],[Region]], 'Cost of Living_Raw'!A:A, 'Cost of Living_Raw'!C:C, "") -> 14.33 | G1815: =(D1815 / F1815) -> 0.69783671
A1816: Southwest Minnesota | B1816: Plant and System Operators | C1816: 19 | D1816: 31.29 | E1816: Production Occupations | F1816: =_xlfn.XLOOKUP(Job_Vacancies6[[#This Row],[Region]], 'Cost of Living_Raw'!A:A, 'Cost of Living_Raw'!C:C, "") -> 14.33 | G1816: =(D1816 / F1816) -> 2.1835311
A1817: Southwest Minnesota | B1817: Stationary Engineers and Boiler Operators | C1817: 8 | D1817: 35.08 | E1817: Production Occupations | F1817: =_xlfn.XLOOKUP(Job_Vacancies6[[#This Row],[Region]], 'Cost of Living_Raw'!A:A, 'Cost of Living_Raw'!C:C, "") -> 14.33 | G1817: =(D1817 / F1817) -> 2.4480112
A1818: Southwest Minnesota | B1818: Water and Wastewater Treatment Plant and System Op | C1818: 7 | D1818: 29.65 | E1818: Production Occupations | F1818: =_xlfn.XLOOKUP(Job_Vacancies6[[#This Row],[Region]], 'Cost of Living_Raw'!A:A, 'Cost of Living_Raw'!C:C, "") -> 14.33 | G1818: =(D1818 / F1818) -> 2.0690858
A1819: Southwest Minnesota | B1819: Other Production Occupations | C1819: 164 | D1819: 16.99 | E1819: Production Occupations | F1819: =_xlfn.XLOOKUP(Job_Vacancies6[[#This Row],[Region]], 'Cost of Living_Raw'!A:A, 'Cost of Living_Raw'!C:C, "") -> 14.33 | G1819: =(D1819 / F1819) -> 1.1856246
A1820: Southwest Minnesota | B1820: Inspectors, Testers, Sorters, Samplers, and Weighe | C1820: 19 | D1820: 19.43 | E1820: Production Occupations | F1820: =_xlfn.XLOOKUP(Job_Vacancies6[[#This Row],[Region]], 'Cost of Living_Raw'!A:A, 'Cost of Living_Raw'!C:C, "") -> 14.33 | G1820: =(D1820 / F1820) -> 1.3558967
A1821: Southwest Minnesota | B1821: Coating, Painting, and Spraying Machine Setters, O | C1821: 4 | D1821: 17.17 | E1821: Production Occupations | F1821: =_xlfn.XLOOKUP(Job_Vacancies6[[#This Row],[Region]], 'Cost of Living_Raw'!A:A, 'Cost of Living_Raw'!C:C, "") -> 14.33 | G1821: =(D1821 / F1821) -> 1.1981856
A1822: Southwest Minnesota | B1822: Computer Numerically Controlled Tool Operators | C1822: 12 | D1822: 17.52 | E1822: Production Occupations | F1822: =_xlfn.XLOOKUP(Job_Vacancies6[[#This Row],[Region]], 'Cost of Living_Raw'!A:A, 'Cost of Living_Raw'!C:C, "") -> 14.33 | G1822: =(D1822 / F1822) -> 1.2226099
A1823: Southwest Minnesota | B1823: Helpers--Production Workers | C1823: 79 | D1823: 12 | E1823: Production Occupations | F1823: =_xlfn.XLOOKUP(Job_Vacancies6[[#This Row],[Region]], 'Cost of Living_Raw'!A:A, 'Cost of Living_Raw'!C:C, "") -> 14.33 | G1823: =(D1823 / F1823) -> 0.83740405
A1824: Southwest Minnesota | B1824: Transportation and Material Moving Occupations | C1824: 1033 | D1824: 21.37 | E1824: Transportation and Material Moving Occupations | F1824: =_xlfn.XLOOKUP(Job_Vacancies6[[#This Row],[Region]], 'Cost of Living_Raw'!A:A, 'Cost of Living_Raw'!C:C, "") -> 14.33 | G1824: =(D1824 / F1824) -> 1.491277
A1825: Southwest Minnesota | B1825: Motor Vehicle Operators | C1825: 660 | D1825: 26.41 | E1825: Transportation and Material Moving Occupations | F1825: =_xlfn.XLOOKUP(Job_Vacancies6[[#This Row],[Region]], 'Cost of Living_Raw'!A:A, 'Cost of Living_Raw'!C:C, "") -> 14.33 | G1825: =(D1825 / F1825) -> 1.8429867
... A1838: Southwest Minnesota | B1838: Apprenticeships | C1838: 25 | D1838: 17.96 | E1838: Unknown | F1838: =_xlfn.XLOOKUP(Job_Vacancies6[[#This Row],[Region]], 'Cost of Living_Raw'!A:A, 'Cost of Living_Raw'!C:C, "") -> 14.33 | G1838: =(D1838 / F1838) -> 1.2533147

Sheet Job Vacancies_Raw
A1: Region | B1: Job Title | C1: Vacancies | D1: medianwage | E1: Job Industry
A2: Seven County Mpls-St Paul, MN | B2: Management Occupations | C2: 4460 | D2: 42.5 | E2: Management Occupations
A3: Seven County Mpls-St Paul, MN | B3: Top Executives | C3: 144 | D3: 39.41 | E3: Management Occupations
A4: Seven County Mpls-St Paul, MN | B4: Chief Executives | C4: 5 | D4: 44.59 | E4: Management Occupations
A5: Seven County Mpls-St Paul, MN | B5: General and Operations Managers | C5: 139 | D5: 38.7 | E5: Management Occupations
A6: Seven County Mpls-St Paul, MN | B6: Advertising, Marketing, Promotions, Public Relatio | C6: 991 | D6: 47.63 | E6: Management Occupations
A7: Seven County Mpls-St Paul, MN | B7: Advertising and Promotions Managers | C7: 9 | D7: 41.88 | E7: Management Occupations
A8: Seven County Mpls-St Paul, MN | B8: Marketing Managers | C8: 597 | D8: 48.59 | E8: Management Occupations
A9: Seven County Mpls-St Paul, MN | B9: Sales Managers | C9: 217 | D9: 53.79 | E9: Management Occupations
A10: Seven County Mpls-St Paul, MN | B10: Public Relations Managers | C10: 25 | D10: 44.54 | E10: Management Occupations
A11: Seven County Mpls-St Paul, MN | B11: Fundraising Managers | C11: 144 | D11: 39.1 | E11: Management Occupations
A12: Seven County Mpls-St Paul, MN | B12: Operations Specialties Managers | C12: 1605 | D12: 55.3 | E12: Management Occupations
A13: Seven County Mpls-St Paul, MN | B13: Administrative Services Managers | C13: 151 | D13: 46.96 | E13: Management Occupations
... A1811: Southwest Minnesota | B1811: Welders, Cutters, Solderers, and Brazers | C1811: 32 | D1811: 25.36 | E1811: Production Occupations
A1812: Southwest Minnesota | B1812: Printing Workers | C1812: 4 | E1812: Production Occupations
A1813: Southwest Minnesota | B1813: Textile, Apparel, and Furnishings Workers | C1813: 85 | D1813: 10 | E1813: Production Occupations
A1814: Southwest Minnesota | B1814: Laundry and Dry-Cleaning Workers | C1814: 85 | D1814: 10 | E1814: Production Occupations
A1815: Southwest Minnesota | B1815: Plant and System Operators | C1815: 19 | D1815: 31.29 | E1815: Production Occupations
A1816: Southwest Minnesota | B1816: Stationary Engineers and Boiler Operators | C1816: 8 | D1816: 35.08 | E1816: Production Occupations
A1817: Southwest Minnesota | B1817: Water and Wastewater Treatment Plant and System Op | C1817: 7 | D1817: 29.65 | E1817: Production Occupations
A1818: Southwest Minnesota | B1818: Other Production Occupations | C1818: 164 | D1818: 16.99 | E1818: Production Occupations
A1819: Southwest Minnesota | B1819: Inspectors, Testers, Sorters, Samplers, and Weighe | C1819: 19 | D1819: 19.43 | E1819: Production Occupations
A1820: Southwest Minnesota | B1820: Coating, Painting, and Spraying Machine Setters, O | C1820: 4 | D1820: 17.17 | E1820: Production Occupations
A1821: Southwest Minnesota | B1821: Computer Numerically Controlled Tool Operators | C1821: 12 | D1821: 17.52 | E1821: Production Occupations
A1822: Southwest Minnesota | B1822: Helpers--Production Workers | C1822: 79 | D1822: 12 | E1822: Production Occupations
A1823: Southwest Minnesota | B1823: Transportation and Material Moving Occupations | C1823: 1033 | D1823: 21.37 | E1823: Transportation and Material Moving Occupations
A1824: Southwest Minnesota | B1824: Motor Vehicle Operators | C1824: 660 | D1824: 26.41 | E1824: Transportation and Material Moving Occupations
... A1837: Southwest Minnesota | B1837: Apprenticeships | C1837: 25 | D1837: 17.96 | E1837: Unknown

Sheet Job Vacancies Raw
A1: Region | B1: Year | C1: occcode | D1: Job Title | E1: Vacancies | F1: medianwage | G1: meanwage
A2: Central Minnesota | B2: 2024 | C2: 112022 | D2: Sales Managers | E2: 13 | F2: 49.8 | G2: 53.08
A3: Central Minnesota | B3: 2024 | C3: 113000 | D3: Operations Specialties Managers | E3: 47 | F3: 49.19 | G3: 49.91
A4: Central Minnesota | B4: 2024 | C4: 113013 | D4: Facilities Managers | E4: 7 | F4: 44.44 | G4: 46.64
A5: Central Minnesota | B5: 2024 | C5: 113021 | D5: Computer and Information Systems Managers | E5: 5 | F5: 45.15 | G5: 49.76
A6: Central Minnesota | B6: 2024 | C6: 113031 | D6: Financial Managers | E6: 14 | F6: 46.51 | G6: 50.23
A7: Central Minnesota | B7: 2024 | C7: 113121 | D7: Human Resources Managers | E7: 10 | F7: 50.35 | G7: 53.19
A8: Central Minnesota | B8: 2024 | C8: 119000 | D8: Other Management Occupations | E8: 199 | F8: 29.22 | G8: 31.11
A9: Central Minnesota | B9: 2024 | C9: 119021 | D9: Construction Managers | E9: 4 | F9: 38.82 | G9: 42.41
A10: Central Minnesota | B10: 2024 | C10: 119032 | D10: Education Administrators, Kindergarten through Sec | E10: 5 | F10: 33.92 | G10: 36.29
A11: Central Minnesota | B11: 2024 | C11: 119033 | D11: Education Administrators, Postsecondary | E11: 8 | F11: 25.89 | G11: 31.43
A12: Central Minnesota | B12: 2024 | C12: 119111 | D12: Medical and Health Services Managers | E12: 128 | F12: 29.54 | G12: 31.18
A13: Central Minnesota | B13: 2024 | C13: 119141 | D13: Property, Real Estate, and Community Association M | E13: 5 | F13: 31.16 | G13: 34.32
... A1274: Southwest Minnesota | B1274: 2024 | C1274: 514121 | D1274: Welders, Cutters, Solderers, and Brazers | E1274: 32 | F1274: 25.36 | G1274: 26.11
A1275: Southwest Minnesota | B1275: 2024 | C1275: 515100 | D1275: Printing Workers | E1275: 4
A1276: Southwest Minnesota | B1276: 2024 | C1276: 516000 | D1276: Textile, Apparel, and Furnishings Workers | E1276: 85 | F1276: 10 | G1276: 10.33
A1277: Southwest Minnesota | B1277: 2024 | C1277: 516011 | D1277: Laundry and Dry-Cleaning Workers | E1277: 85 | F1277: 10 | G1277: 10.33
A1278: Southwest Minnesota | B1278: 2024 | C1278: 518000 | D1278: Plant and System Operators | E1278: 19 | F1278: 31.29 | G1278: 33.49
A1279: Southwest Minnesota | B1279: 2024 | C1279: 518021 | D1279: Stationary Engineers and Boiler Operators | E1279: 8 | F1279: 35.08 | G1279: 37.37
A1280: Southwest Minnesota | B1280: 2024 | C1280: 518031 | D1280: Water and Wastewater Treatment Plant and System Op | E1280: 7 | F1280: 29.65 | G1280: 31.52
A1281: Southwest Minnesota | B1281: 2024 | C1281: 519000 | D1281: Other Production Occupations | E1281: 164 | F1281: 16.99 | G1281: 17.41
A1282: Southwest Minnesota | B1282: 2024 | C1282: 519061 | D1282: Inspectors, Testers, Sorters, Samplers, and Weighe | E1282: 19 | F1282: 19.43 | G1282: 21.02
A1283: Southwest Minnesota | B1283: 2024 | C1283: 519124 | D1283: Coating, Painting, and Spraying Machine Setters, O | E1283: 4 | F1283: 17.17 | G1283: 18.61
A1284: Southwest Minnesota | B1284: 2024 | C1284: 519161 | D1284: Computer Numerically Controlled Tool Operators | E1284: 12 | F1284: 17.52 | G1284: 19.2
A1285: Southwest Minnesota | B1285: 2024 | C1285: 519198 | D1285: Helpers--Production Workers | E1285: 79 | F1285: 12 | G1285: 13.9
A1286: Southwest Minnesota | B1286: 2024 | C1286: 530000 | D1286: Transportation and Material Moving Occupations | E1286: 1033 | F1286: 21.37 | G1286: 22.85
A1287: Southwest Minnesota | B1287: 2024 | C1287: 533000 | D1287: Motor Vehicle Operators | E1287: 660 | F1287: 26.41 | G1287: 26.57
... A1842: Seven County Mpls-St Paul, MN | B1842: 2024 | C1842: 920000 | D1842: Apprenticeships | E1842: 198 | F1842: 16.68 | G1842: 17.88

Sheet Sheet4

Sheet UI Claim_Raw
A1: Region | B1: Date | C1: Job Industry | D1: Claimants
A2: Northwest Minnesota | B2: 45627 | C2: Business and Financial Operations Occupations
A3: Northwest Minnesota | B3: 45597 | C3: Business and Financial Operations Occupations
A4: Northwest Minnesota | B4: 45474 | C4: Business and Financial Operations Occupations
A5: Northwest Minnesota | B5: 45352 | C5: Business and Financial Operations Occupations
A6: Northwest Minnesota | B6: 45323 | C6: Business and Financial Operations Occupations
A7: Northwest Minnesota | B7: 45627 | C7: Computer and Mathematical Occupations
A8: Northwest Minnesota | B8: 45597 | C8: Computer and Mathematical Occupations
A9: Northwest Minnesota | B9: 45536 | C9: Computer and Mathematical Occupations
A10: Northwest Minnesota | B10: 45505 | C10: Computer and Mathematical Occupations
A11: Northwest Minnesota | B11: 45474 | C11: Computer and Mathematical Occupations
A12: Northwest Minnesota | B12: 45444 | C12: Computer and Mathematical Occupations
A13: Northwest Minnesota | B13: 45413 | C13: Computer and Mathematical Occupations
... A476: Seven County Mpls-St Paul, MN | B476: 45292 | C476: Military Specific Occupations
A477: Southwest Minnesota | B477: 45627 | C477: Management Occupations | D477: 414
A478: Southwest Minnesota | B478: 45597 | C478: Management Occupations | D478: 342
A479: Southwest Minnesota | B479: 45566 | C479: Management Occupations | D479: 207
A480: Southwest Minnesota | B480: 45536 | C480: Management Occupations | D480: 207
A481: Southwest Minnesota | B481: 45505 | C481: Management Occupations | D481: 162
A482: Southwest Minnesota | B482: 45474 | C482: Management Occupations | D482: 270
A483: Southwest Minnesota | B483: 45444 | C483: Management Occupations | D483: 288
A484: Southwest Minnesota | B484: 45413 | C484: Management Occupations | D484: 243
A485: Southwest Minnesota | B485: 45383 | C485: Management Occupations | D485: 234
A486: Southwest Minnesota | B486: 45352 | C486: Management Occupations | D486: 153
A487: Southwest Minnesota | B487: 45323 | C487: Management Occupations | D487: 189
A488: Southwest Minnesota | B488: 45292 | C488: Management Occupations | D488: 225
... A1715: Seven County Mpls-St Paul, MN | B1715: 45292 | C1715: Unknown | D1715: 11277

Sheet UI Claim Raw
A1: Region | B1: Date | C1: Job Title | D1: Current
A2: Central Minnesota | B2: 45627 | C2: Management Occupations | D2: 465
A3: Central Minnesota | B3: 45597 | C3: Management Occupations | D3: 498
A4: Central Minnesota | B4: 45566 | C4: Management Occupations | D4: 467
A5: Central Minnesota | B5: 45536 | C5: Management Occupations | D5: 369
A6: Central Minnesota | B6: 45505 | C6: Management Occupations | D6: 538
A7: Central Minnesota | B7: 45474 | C7: Management Occupations | D7: 352
A8: Central Minnesota | B8: 45444 | C8: Management Occupations | D8: 393
A9: Central Minnesota | B9: 45413 | C9: Management Occupations | D9: 353
A10: Central Minnesota | B10: 45383 | C10: Management Occupations | D10: 323
A11: Central Minnesota | B11: 45352 | C11: Management Occupations | D11: 298
A12: Central Minnesota | B12: 45323 | C12: Management Occupations | D12: 354
A13: Central Minnesota | B13: 45292 | C13: Management Occupations | D13: 502
... A49: Central Minnesota | B49: 45292 | C49: Architecture and Engineering Occupations | D49: 132
A50: Central Minnesota | B50: 45536 | C50: Life, Physical, and Social Science Occupations
A51: Central Minnesota | B51: 45505 | C51: Life, Physical, and Social Science Occupations
A52: Central Minnesota | B52: 45474 | C52: Life, Physical, and Social Science Occupations
A53: Central Minnesota | B53: 45444 | C53: Life, Physical, and Social Science Occupations
A54: Central Minnesota | B54: 45413 | C54: Life, Physical, and Social Science Occupations
A55: Central Minnesota | B55: 45627 | C55: Life, Physical, and Social Science Occupations
A56: Central Minnesota | B56: 45597 | C56: Life, Physical, and Social Science Occupations
A57: Central Minnesota | B57: 45566 | C57: Life, Physical, and Social Science Occupations
A58: Central Minnesota | B58: 45383 | C58: Life, Physical, and Social Science Occupations
A59: Central Minnesota | B59: 45352 | C59: Life, Physical, and Social Science Occupations
A60: Central Minnesota | B60: 45323 | C60: Life, Physical, and Social Science Occupations
A61: Central Minnesota | B61: 45292 | C61: Life, Physical, and Social Science Occupations
... A65: Central Minnesota | B65: 45536 | C65: Community and Social Services Occupations
A66: Central Minnesota | B66: 45505 | C66: Community and Social Services Occupations | D66: 48
A67: Central Minnesota | B67: 45474 | C67: Community and Social Services Occupations
A68: Central Minnesota | B68: 45444 | C68: Community and Social Services Occupations | D68: 84
A69: Central Minnesota | B69: 45413 | C69: Community and Social Services Occupations | D69: 44
A70: Central Minnesota | B70: 45383 | C70: Community and Social Services Occupations
A71: Central Minnesota | B71: 45352 | C71: Community and Social Services Occupations
A72: Central Minnesota | B72: 45323 | C72: Community and Social Services Occupations
A73: Central Minnesota | B73: 45292 | C73: Community and Social Services Occupations | D73: 52
A74: Central Minnesota | B74: 45627 | C74: Legal Occupations
A75: Central Minnesota | B75: 45597 | C75: Legal Occupations
A76: Central Minnesota | B76: 45566 | C76: Legal Occupations
A77: Central Minnesota | B77: 45536 | C77: Legal Occupations
A78: Central Minnesota | B78: 45505 | C78: Legal Occupations
A79: Central Minnesota | B79: 45474 | C79: Legal Occupations
A80: Central Minnesota | B80: 45444 | C80: Legal Occupations
A81: Central Minnesota | B81: 45413 | C81: Legal Occupations
A82: Central Minnesota | B82: 45383 | C82: Legal Occupations
A83: Central Minnesota | B83: 45352 | C83: Legal Occupations
A84: Central Minnesota | B84: 45323 | C84: Legal Occupations
A85: Central Minnesota | B85: 45292 | C85: Legal Occupations
A86: Central Minnesota | B86: 45627 | C86: Education, Training, and Library Occupations | D86: 640
A87: Central Minnesota | B87: 45597 | C87: Education, Training, and Library Occupations | D87: 161
A88: Central Minnesota | B88: 45566 | C88: Education, Training, and Library Occupations | D88: 220
A89: Central Minnesota | B89: 45536 | C89: Education, Training, and Library Occupations | D89: 265
A90: Central Minnesota | B90: 45505 | C90: Education, Training, and Library Occupations | D90: 630
A91: Central Minnesota | B91: 45474 | C91: Education, Training, and Library Occupations | D91: 1634
A92: Central Minnesota | B92: 45444 | C92: Education, Training, and Library Occupations | D92: 10233
A93: Central Minnesota | B93: 45413 | C93: Education, Training, and Library Occupations | D93: 2509
A94: Central Minnesota | B94: 45383 | C94: Education, Training, and Library Occupations | D94: 148
A95: Central Minnesota | B95: 45352 | C95: Education, Training, and Library Occupations | D95: 112
A96: Central Minnesota | B96: 45323 | C96: Education, Training, and Library Occupations | D96: 48
A97: Central Minnesota | B97: 45292 | C97: Education, Training, and Library Occupations | D97: 392
A98: Central Minnesota | B98: 45627 | C98: Arts, Design, Entertainment, Sports, and Media Occ
A99: Central Minnesota | B99: 45597 | C99: Arts, Design, Entertainment, Sports, and Media Occ
A100: Central Minnesota | B100: 45566 | C100: Arts, Design, Entertainment, Sports, and Media Occ | D100: 52
A101: Central Minnesota | B101: 45536 | C101: Arts, Design, Entertainment, Sports, and Media Occ
A102: Central Minnesota | B102: 45505 | C102: Arts, Design, Entertainment, Sports, and Media Occ
A103: Central Minnesota | B103: 45474 | C103: Arts, Design, Entertainment, Sports, and Media Occ
A104: Central Minnesota | B104: 45444 | C104: Arts, Design, Entertainment, Sports, and Media Occ | D104: 68
A105: Central Minnesota | B105: 45413 | C105: Arts, Design, Entertainment, Sports, and Media Occ | D105: 48
A106: Central Minnesota | B106: 45383 | C106: Arts, Design, Entertainment, Sports, and Media Occ | D106: 48
A107: Central Minnesota | B107: 45352 | C107: Arts, Design, Entertainment, Sports, and Media Occ | D107: 44
A108: Central Minnesota | B108: 45323 | C108: Arts, Design, Entertainment, Sports, and Media Occ | D108: 40
A109: Central Minnesota | B109: 45292 | C109: Arts, Design, Entertainment, Sports, and Media Occ | D109: 84
A110: Central Minnesota | B110: 45627 | C110: Healthcare Practitioners and Technical Occupations | D110: 60
A111: Central Minnesota | B111: 45597 | C111: Healthcare Practitioners and Technical Occupations | D111: 80
A112: Central Minnesota | B112: 45566 | C112: Healthcare Practitioners and Technical Occupations | D112: 60
A113: Central Minnesota | B113: 45536 | C113: Healthcare Practitioners and Technical Occupations | D113: 110
A114: Central Minnesota | B114: 45505 | C114: Healthcare Practitioners and Technical Occupations | D114: 80
A115: Central Minnesota | B115: 45474 | C115: Healthcare Practitioners and Technical Occupations | D115: 167
... A133: Central Minnesota | B133: 45292 | C133: Healthcare Support Occupations | D133: 307
A134: Central Minnesota | B134: 45627 | C134: Protective Service Occupations
A135: Central Minnesota | B135: 45597 | C135: Protective Service Occupations
A136: Central Minnesota | B136: 45566 | C136: Protective Service Occupations
A137: Central Minnesota | B137: 45536 | C137: Protective Service Occupations
A138: Central Minnesota | B138: 45505 | C138: Protective Service Occupations
A139: Central Minnesota | B139: 45474 | C139: Protective Service Occupations
A140: Central Minnesota | B140: 45444 | C140: Protective Service Occupations
A141: Central Minnesota | B141: 45413 | C141: Protective Service Occupations
A142: Central Minnesota | B142: 45383 | C142: Protective Service Occupations
A143: Central Minnesota | B143: 45352 | C143: Protective Service Occupations
A144: Central Minnesota | B144: 45323 | C144: Protective Service Occupations
A145: Central Minnesota | B145: 45292 | C145: Protective Service Occupations
A146: Central Minnesota | B146: 45627 | C146: Food Preparation and Serving Related Occupations | D146: 584
A147: Central Minnesota | B147: 45597 | C147: Food Preparation and Serving Related Occupations | D147: 271
A148: Central Minnesota | B148: 45566 | C148: Food Preparation and Serving Related Occupations | D148: 438
A149: Central Minnesota | B149: 45536 | C149: Food Preparation and Serving Related Occupations | D149: 344
A150: Central Minnesota | B150: 45505 | C150: Food Preparation and Serving Related Occupations | D150: 399
A151: Central Minnesota | B151: 45474 | C151: Food Preparation and Serving Related Occupations | D151: 643
A152: Central Minnesota | B152: 45444 | C152: Food Preparation and Serving Related Occupations | D152: 2624
A153: Central Minnesota | B153: 45413 | C153: Food Preparation and Serving Related Occupations | D153: 784
A154: Central Minnesota | B154: 45383 | C154: Food Preparation and Serving Related Occupations | D154: 389
A155: Central Minnesota | B155: 45352 | C155: Food Preparation and Serving Related Occupations | D155: 499
...

Sheet Employment_Raw
A1: Date | B1: Region | C1: Employment Total
A2: 45292 | B2: Seven County Mpls-St Paul, MN | C2: 1697030
A3: 45292 | B3: Northwest Minnesota | C3: 280371
A4: 45292 | B4: Northeast Minnesota | C4: 150872
A5: 45292 | B5: Southeast Minnesota | C5: 269507
A6: 45292 | B6: Southwest Minnesota | C6: 204271
A7: 45292 | B7: Central Minnesota | C7: 386953
A8: 45323 | B8: Seven County Mpls-St Paul, MN | C8: 1698225
A9: 45323 | B9: Northwest Minnesota | C9: 280641
A10: 45323 | B10: Northeast Minnesota | C10: 152129
A11: 45323 | B11: Southeast Minnesota | C11: 269947
A12: 45323 | B12: Southwest Minnesota | C12: 204729
A13: 45323 | B13: Central Minnesota | C13: 387529
... A73: 45627 | B73: Central Minnesota | C73: 393788

Sheet Employment Raw Data
A1: Year/Month | B1: Region | C1: Employment Total
A2: 45292 | B2: Seven County Mpls-St Paul - MN | C2: 1697030
A3: 45292 | B3: Northwest Minnesota | C3: 280371
A4: 45292 | B4: Northeast Minnesota | C4: 150872
A5: 45292 | B5: Southeast Minnesota | C5: 269507
A6: 45292 | B6: Southwest Minnesota | C6: 204271
A7: 45292 | B7: Central Minnesota | C7: 386953
A8: 45323 | B8: Seven County Mpls-St Paul - MN | C8: 1698225
A9: 45323 | B9: Northwest Minnesota | C9: 280641
A10: 45323 | B10: Northeast Minnesota | C10: 152129
A11: 45323 | B11: Southeast Minnesota | C11: 269947
A12: 45323 | B12: Southwest Minnesota | C12: 204729
A13: 45323 | B13: Central Minnesota | C13: 387529
... A73: 45627 | B73: Central Minnesota | C73: 393788

Sheet Unemployment_Raw
A1: Date | B1: Region | C1: Unemployment Total
A2: 45292 | B2: Seven County Mpls-St Paul, MN | C2: 49076
A3: 45292 | B3: Northwest Minnesota | C3: 14411
A4: 45292 | B4: Northeast Minnesota | C4: 6968
A5: 45292 | B5: Southeast Minnesota | C5: 8702
A6: 45292 | B6: Southwest Minnesota | C6: 7809
A7: 45292 | B7: Central Minnesota | C7: 17433
A8: 45323 | B8: Seven County Mpls-St Paul, MN | C8: 53496
A9: 45323 | B9: Northwest Minnesota | C9: 14617
A10: 45323 | B10: Northeast Minnesota | C10: 7401
A11: 45323 | B11: Southeast Minnesota | C11: 9342
A12: 45323 | B12: Southwest Minnesota | C12: 8253
A13: 45323 | B13: Central Minnesota | C13: 18033
... A73: 45627 | B73: Central Minnesota | C73: 13245

Sheet Unemployment Raw Data
A1: Year/Month | B1: Region | C1: Unemployment Total
A2: 45292 | B2: Seven County Mpls-St Paul - MN | C2: 49076
A3: 45292 | B3: Northwest Minnesota | C3: 14411
A4: 45292 | B4: Northeast Minnesota | C4: 6968
A5: 45292 | B5: Southeast Minnesota | C5: 8702
A6: 45292 | B6: Southwest Minnesota | C6: 7809
A7: 45292 | B7: Central Minnesota | C7: 17433
A8: 45323 | B8: Seven County Mpls-St Paul - MN | C8: 53496
A9: 45323 | B9: Northwest Minnesota | C9: 14617
A10: 45323 | B10: Northeast Minnesota | C10: 7401
A11: 45323 | B11: Southeast Minnesota | C11: 9342
A12: 45323 | B12: Southwest Minnesota | C12: 8253
A13: 45323 | B13: Central Minnesota | C13: 18033
... A73: 45627 | B73: Central Minnesota | C73: 13245

Sheet Job Turnover_Raw
A1: Activity | B1: Date | C1: Total
A2: Hires | B2: 45292 | C2: 111000
A3: Layoffs and Discharges | B3: 45292 | C3: 38000
A4: Quits | B4: 45292 | C4: 50000
A5: Job Openings | B5: 45292 | C5: 196000
A6: Total Seperations | B6: 45292 | C6: 101000
A7: Quits | B7: 45323 | C7: 44000
A8: Layoffs and Discharges | B8: 45323 | C8: 30000
A9: Total Seperations | B9: 45323 | C9: 78000
A10: Job Openings | B10: 45323 | C10: 145000
A11: Hires | B11: 45323 | C11: 74000
A12: Layoffs and Discharges | B12: 45352 | C12: 28000
A13: Hires | B13: 45352 | C13: 77000
... A61: Total Seperations | B61: 45627 | C61: 91000

Sheet Job Turn Over Data
A1: Activity | B1: Month Year | C1: Value
A2: Hires | B2: 45292 | C2: 111
A3: Layoffs and Discharges | B3: 45292 | C3: 38
A4: Quits | B4: 45292 | C4: 50
A5: Job Openings | B5: 45292 | C5: 196
A6: Total Seperations | B6: 45292 | C6: 101
A7: Quits | B7: 45323 | C7: 44
A8: Layoffs and Discharges | B8: 45323 | C8: 30
A9: Total Seperations | B9: 45323 | C9: 78
A10: Job Openings | B10: 45323 | C10: 145
A11: Hires | B11: 45323 | C11: 74
A12: Layoffs and Discharges | B12: 45352 | C12: 28
A13: Hires | B13: 45352 | C13: 77
... A61: Total Seperations | B61: 45627 | C61: 91

Sheet Cost of Living_Raw
A1: Region | B1: Yearly Cost | C1: Hourly Wage | D1: Child Care | E1: Food | F1: Health Care | G1: Housing | H1: Transport | I1: Other | J1: Taxes | K1: Date | L1: EstMonthly Cost
A2: Northeast Minnesota | B2: 31188 | C2: 14.99 | D2: 0 | E2: 413 | F2: 150 | G2: 857 | H2: 573 | I2: 294 | J2: 312 | K2: 45292 | L2: 2599
A3: Central Minnesota | B3: 36468 | C3: 17.53 | D3: 0 | E3: 414 | F3: 155 | G3: 1099 | H3: 630 | I3: 350 | J3: 391 | K3: 45292 | L3: 3039
A4: Northwest Minnesota | B4: 30744 | C4: 14.78 | D4: 0 | E4: 416 | F4: 151 | G4: 792 | H4: 614 | I4: 279 | J4: 310 | K4: 45292 | L4: 2562
A5: Southeast Minnesota | B5: 31872 | C5: 15.32 | D5: 0 | E5: 417 | F5: 151 | G5: 884 | H5: 581 | I5: 301 | J5: 322 | K5: 45292 | L5: 2656
A6: Seven County Mpls-St Paul, MN | B6: 40212 | C6: 19.33 | D6: 0 | E6: 430 | F6: 159 | G6: 1356 | H6: 554 | I6: 413 | J6: 439 | K6: 45292 | L6: 3351
A7: Southwest Minnesota | B7: 29808 | C7: 14.33 | D7: 0 | E7: 418 | F7: 150 | G7: 793 | H7: 550 | I7: 280 | J7: 293 | K7: 45292 | L7: 2484
A8: Northeast Minnesota | B8: 31188 | C8: 14.99 | D8: 0 | E8: 413 | F8: 150 | G8: 857 | H8: 573 | I8: 294 | J8: 312 | K8: 45324 | L8: 2599
A9: Central Minnesota | B9: 36468 | C9: 17.53 | D9: 0 | E9: 414 | F9: 155 | G9: 1099 | H9: 630 | I9: 350 | J9: 391 | K9: 45324 | L9: 3039
A10: Northwest Minnesota | B10: 30744 | C10: 14.78 | D10: 0 | E10: 416 | F10: 151 | G10: 792 | H10: 614 | I10: 279 | J10: 310 | K10: 45324 | L10: 2562
A11: Southeast Minnesota | B11: 31872 | C11: 15.32 | D11: 0 | E11: 417 | F11: 151 | G11: 884 | H11: 581 | I11: 301 | J11: 322 | K11: 45324 | L11: 2656
A12: Seven County Mpls-St Paul, MN | B12: 40212 | C12: 19.33 | D12: 0 | E12: 430 | F12: 159 | G12: 1356 | H12: 554 | I12: 413 | J12: 439 | K12: 45324 | L12: 3351
A13: Southwest Minnesota | B13: 29808 | C13: 14.33 | D13: 0 | E13: 418 | F13: 150 | G13: 793 | H13: 550 | I13: 280 | J13: 293 | K13: 45324 | L13: 2484
... A73: Southwest Minnesota | B73: 29808 | C73: 14.33 | D73: 0 | E73: 418 | F73: 150 | G73: 793 | H73: 550 | I73: 280 | J73: 293 | K73: 45632 | L73: 2484

Sheet COL Raw
A1: Region | B1: Family Size | C1: Number of Adults | D1: Number of Workers | E1: Number of Children | F1: Age of Adults | G1: Yearly Cost | H1: Hourly Wage | I1: Child Care | J1: Food | K1: Health Care | L1: Housing | M1: Transport | N1: Other | O1: Taxes | P1: Year | Q1: Date | R1: Job Industry
A2: Northeast Minnesota | B2: 1 | C2: 1 | D2: 1 | E2: 0 | F2: 19-50 | G2: 31188 | H2: 14.99 | I2: 0 | J2: 413 | K2: 150 | L2: 857 | M2: 573 | N2: 294 | O2: 312 | P2: 2024 | Q2: 45292 | R2: All Industries
A3: Central Minnesota | B3: 1 | C3: 1 | D3: 1 | E3: 0 | F3: 19-50 | G3: 36468 | H3: 17.53 | I3: 0 | J3: 414 | K3: 155 | L3: 1099 | M3: 630 | N3: 350 | O3: 391 | P3: 2024 | Q3: 45292 | R3: All Industries
A4: Northwest Minnesota | B4: 1 | C4: 1 | D4: 1 | E4: 0 | F4: 19-50 | G4: 30744 | H4: 14.78 | I4: 0 | J4: 416 | K4: 151 | L4: 792 | M4: 614 | N4: 279 | O4: 310 | P4: 2024 | Q4: 45292 | R4: All Industries
A5: Southeast Minnesota | B5: 1 | C5: 1 | D5: 1 | E5: 0 | F5: 19-50 | G5: 31872 | H5: 15.32 | I5: 0 | J5: 417 | K5: 151 | L5: 884 | M5: 581 | N5: 301 | O5: 322 | P5: 2024 | Q5: 45292 | R5: All Industries
A6: Seven County Mpls-St Paul, MN | B6: 1 | C6: 1 | D6: 1 | E6: 0 | F6: 19-50 | G6: 40212 | H6: 19.33 | I6: 0 | J6: 430 | K6: 159 | L6: 1356 | M6: 554 | N6: 413 | O6: 439 | P6: 2024 | Q6: 45292 | R6: All Industries
A7: Southwest Minnesota | B7: 1 | C7: 1 | D7: 1 | E7: 0 | F7: 19-50 | G7: 29808 | H7: 14.33 | I7: 0 | J7: 418 | K7: 150 | L7: 793 | M7: 550 | N7: 280 | O7: 293 | P7: 2024 | Q7: 45292 | R7: All Industries
A8: Northeast Minnesota | B8: 1 | C8: 1 | D8: 1 | E8: 0 | F8: 19-50 | G8: 31188 | H8: 14.99 | I8: 0 | J8: 413 | K8: 150 | L8: 857 | M8: 573 | N8: 294 | O8: 312 | P8: 2024 | Q8: 45324 | R8: All Industries
A9: Central Minnesota | B9: 1 | C9: 1 | D9: 1 | E9: 0 | F9: 19-50 | G9: 36468 | H9: 17.53 | I9: 0 | J9: 414 | K9: 155 | L9: 1099 | M9: 630 | N9: 350 | O9: 391 | P9: 2024 | Q9: 45324 | R9: All Industries
A10: Northwest Minnesota | B10: 1 | C10: 1 | D10: 1 | E10: 0 | F10: 19-50 | G10: 30744 | H10: 14.78 | I10: 0 | J10: 416 | K10: 151 | L10: 792 | M10: 614 | N10: 279 | O10: 310 | P10: 2024 | Q10: 45324 | R10: All Industries
A11: Southeast Minnesota | B11: 1 | C11: 1 | D11: 1 | E11: 0 | F11: 19-50 | G11: 31872 | H11: 15.32 | I11: 0 | J11: 417 | K11: 151 | L11: 884 | M11: 581 | N11: 301 | O11: 322 | P11: 2024 | Q11: 45324 | R11: All Industries
A12: Seven County Mpls-St Paul, MN | B12: 1 | C12: 1 | D12: 1 | E12: 0 | F12: 19-50 | G12: 40212 | H12: 19.33 | I12: 0 | J12: 430 | K12: 159 | L12: 1356 | M12: 554 | N12: 413 | O12: 439 | P12: 2024 | Q12: 45324 | R12: All Industries
A13: Southwest Minnesota | B13: 1 | C13: 1 | D13: 1 | E13: 0 | F13: 19-50 | G13: 29808 | H13: 14.33 | I13: 0 | J13: 418 | K13: 150 | L13: 793 | M13: 550 | N13: 280 | O13: 293 | P13: 2024 | Q13: 45324 | R13: All Industries
... A73: Southwest Minnesota | B73: 1 | C73: 1 | D73: 1 | E73: 0 | F73: 19-50 | G73: 29808 | H73: 14.33 | I73: 0 | J73: 418 | K73: 150 | L73: 793 | M73: 550 | N73: 280 | O73: 293 | P73: 2024 | Q73: 45632 | R73: All Industries

Sheet Sheet1
A2: Region | B2: Sum of Vacancies | D2: Claimants | E2: Vacancy Pressure
A3: Central Minnesota | B3: 39319 | D3: 414 | E3: =B3/D3 -> 94.97343
A4: Northeast Minnesota | B4: 23866 | D4: 342 | E4: =B4/D4 -> 69.783626
A5: Northwest Minnesota | B5: 36635 | D5: 207 | E5: =B5/D5 -> 176.98068
A6: Seven County Mpls-St Paul, MN | B6: 197334 | D6: 207 | E6: =B6/D6 -> 953.30435
A7: Southeast Minnesota | B7: 28152 | D7: 162 | E7: =B7/D7 -> 173.77778
A8: Southwest Minnesota | B8: 25551 | D8: 270 | E8: =B8/D8 -> 94.633333
A9: Grand Total | B9: 350857 | D9: 288 | E9: =B9/D9 -> 1218.2535
D10: 243 | E10: =B10/D10 -> 0
A11: Industry | B11: Vacancy Pressure
A12: Central Minnesota | B12: 0.21483679
A13: Northeast Minnesota | B13: 0.20521419
A14: Northwest Minnesota | B14: 0.22365417
A15: Seven County Mpls-St Paul, MN | B15: 0.21992613
A16: Southeast Minnesota | B16: 0.12766363
A17: Southwest Minnesota | B17: 0.16295281
D36: 99 | E36: =B36/D36 -> 0
D37: 108 | E37: =B37/D37 -> 0
D38: 144 | E38: =B38/D38 -> 0
D39: 90 | E39: =B39/D39 -> 0
D40: 234 | E40: =B40/D40 -> 0
D41: 144 | E41: =B41/D41 -> 0
D42: 135 | E42: =B42/D42 -> 0
D43: 279 | E43: =B43/D43 -> 0
D44: 171 | E44: =B44/D44 -> 0
D45: 333 | E45: =B45/D45 -> 0
D46: 279 | E46: =B46/D46 -> 0
D47: 216 | E47: =B47/D47 -> 0
... D1716: 11277 | E1716: =B1716/D1716 -> 0

Sheet Sheet2
A2: Region | B2: Average of medianwage | C2: Region | E2: Hourly Wage | F2: Wage Sufficiency
A3: Central Minnesota | B3: 24.828014 | C3: Northeast Minnesota | E3: 14.99 | F3: =B3/E3 -> 1.6563052
A4: Northeast Minnesota | B4: 26.823559 | C4: Central Minnesota | E4: 17.53 | F4: =B4/E4 -> 1.5301517
A5: Northwest Minnesota | B5: 22.853016 | C5: Northwest Minnesota | E5: 14.78 | F5: =B5/E5 -> 1.5462122
A6: Seven County Mpls-St Paul, MN | B6: 28.889704 | C6: Southeast Minnesota | E6: 15.32 | F6: =B6/E6 -> 1.8857509
A7: Southeast Minnesota | B7: 26.345488 | C7: Seven County Mpls-St Paul, MN | E7: 19.33 | F7: =B7/E7 -> 1.3629327
A8: Southwest Minnesota | B8: 23.811078 | C8: Southwest Minnesota | E8: 14.33 | F8: =B8/E8 -> 1.6616244
A9: Grand Total | B9: 26.127951 | C9: Northeast Minnesota | E9: 14.99 | F9: =B9/E9 -> 1.7430254
C10: Central Minnesota | E10: 17.53 | F10: =B10/E10 -> 0
C11: Northwest Minnesota | E11: 14.78 | F11: =B11/E11 -> 0
C12: Southeast Minnesota | E12: 15.32 | F12: =B12/E12 -> 0
C13: Seven County Mpls-St Paul, MN | E13: 19.33 | F13: =B13/E13 -> 0
C14: Southwest Minnesota | E14: 14.33 | F14: =B14/E14 -> 0
C15: Northeast Minnesota | E15: 14.99 | F15: =B15/E15 -> 0
C16: Central Minnesota | E16: 17.53 | F16: =B16/E16 -> 0
C17: Northwest Minnesota | E17: 14.78 | F17: =B17/E17 -> 0
C18: Southeast Minnesota | E18: 15.32 | F18: =B18/E18 -> 0
C19: Seven County Mpls-St Paul, MN | E19: 19.33 | F19: =B19/E19 -> 0
C20: Southwest Minnesota | E20: 14.33 | F20: =B20/E20 -> 0
C21: Northeast Minnesota | E21: 14.99 | F21: =B21/E21 -> 0
... C74: Southwest Minnesota | E74: 14.33 | F74: =B74/E74 -> 0

Sheet Sheet3
A1: Region | B1: Sum of Claimants | C1: Region | D1: Employment Total | E1: Claim Intensity (%)
A2: Central Minnesota | B2: 183018 | C2: Seven County Mpls-St Paul, MN | D2: 1697030 | E2: =B2/D2 -> 0.10784606
A3: Northeast Minnesota | B3: 116298 | C3: Northwest Minnesota | D3: 280371 | E3: =B3/D3 -> 0.41480039
A4: Northwest Minnesota | B4: 163802 | C4: Northeast Minnesota | D4: 150872 | E4: =B4/D4 -> 1.0857018
A5: Seven County Mpls-St Paul, MN | B5: 897274 | C5: Southeast Minnesota | D5: 269507 | E5: =B5/D5 -> 3.3293161
A6: Southeast Minnesota | B6: 220517 | C6: Southwest Minnesota | D6: 204271 | E6: =B6/D6 -> 1.0795316
A7: Southwest Minnesota | B7: 156800 | C7: Central Minnesota | D7: 386953 | E7: =B7/D7 -> 0.40521717
A8: Grand Total | B8: 1737709 | C8: Seven County Mpls-St Paul, MN | D8: 1698225 | E8: =B8/D8 -> 1.0232502
C9: Northwest Minnesota | D9: 280641 | E9: =B9/D9 -> 0
A10: Region | B10: UI Claim Intensity | C10: Northeast Minnesota | D10: 152129 | E10: =#REF!/D10 -> #REF!
A11: Central Minnesota | B11: 0.037454851 | C11: Southeast Minnesota | D11: 269947 | E11: =#REF!/D11 -> #REF!
A12: Northeast Minnesota | B12: 0.060817425 | C12: Southwest Minnesota | D12: 204729 | E12: =#REF!/D12 -> #REF!
A13: Northwest Minnesota | B13: 0.045306142 | C13: Central Minnesota | D13: 387529 | E13: =#REF!/D13 -> #REF!
A14: Seven County Mpls-St Paul, MN | B14: 0.042424848 | C14: Seven County Mpls-St Paul, MN | D14: 1704198 | E14: =#REF!/D14 -> #REF!
A15: Southeast Minnesota | B15: 0.064967679 | C15: Northwest Minnesota | D15: 284574 | E15: =#REF!/D15 -> #REF!
A16: Southwest Minnesota | B16: 0.060317065 | C16: Northeast Minnesota | D16: 153213 | E16: =#REF!/D16 -> #REF!
C17: Southeast Minnesota | D17: 273313 | E17: =B17/D17 -> 0
C18: Southwest Minnesota | D18: 208572 | E18: =B18/D18 -> 0
C19: Central Minnesota | D19: 390410 | E19: =B19/D19 -> 0
C20: Seven County Mpls-St Paul, MN | D20: 1716175 | E20: =B20/D20 -> 0
C21: Northwest Minnesota | D21: 288863 | E21: =B21/D21 -> 0
C22: Northeast Minnesota | D22: 153582 | E22: =B22/D22 -> 0
C23: Southeast Minnesota | D23: 274333 | E23: =B23/D23 -> 0
C24: Southwest Minnesota | D24: 209624 | E24: =B24/D24 -> 0
C25: Central Minnesota | D25: 393209 | E25: =B25/D25 -> 0
C26: Seven County Mpls-St Paul, MN | D26: 1721191 | E26: =B26/D26 -> 0
C27: Northwest Minnesota | D27: 291301 | E27: =B27/D27 -> 0
C28: Northeast Minnesota | D28: 154003 | E28: =B28/D28 -> 0
... C73: Central Minnesota | D73: 393788 | E73: =B73/D73 -> 0
